beamcalc/__init__.py
beamcalc/analysis.py
beamcalc/beam.py
beamcalc/deflections.py
beamcalc/elements.py
beamcalc/materials.py
beamcalc/sections.py
beamcalc/solver.py
beamcalc_rc-0.0.2.dist-info/licenses/LICENSE
beamcalc_rc-0.0.2.dist-info/METADATA
beamcalc_rc-0.0.2.dist-info/WHEEL
beamcalc_rc-0.0.2.dist-info/top_level.txt
beamcalc_rc-0.0.2.dist-info/RECORD
