Metadata-Version: 2.4
Name: beamcalc-rc
Version: 0.0.2
Summary: Reinforced concrete beam displacements calculator in Python, considering loss of inertia due to crackling.
Home-page: https://github.com/pgalan94/beamcalc-rc
Author: Pedro Déo
Author-email: pgalan94@gmail.com
License: MIT
Classifier: Programming Language :: Python :: 3
Classifier: License :: OSI Approved :: MIT License
Classifier: Operating System :: OS Independent
Classifier: Topic :: Scientific/Engineering
Requires-Python: >=3.10
License-File: LICENSE
Dynamic: license-file
